nevermined_contracts/__init__.py
nevermined_contracts/artifacts/placeholder
nevermined_contracts-3.5.0.dist-info/LICENSE
nevermined_contracts-3.5.0.dist-info/METADATA
nevermined_contracts-3.5.0.dist-info/NOTICE
nevermined_contracts-3.5.0.dist-info/WHEEL
nevermined_contracts-3.5.0.dist-info/top_level.txt
nevermined_contracts-3.5.0.dist-info/RECORD
