Metadata-Version: 2.1
Name: nevermined-contracts
Version: 3.5.0
Summary: Smart Contracts for Nevermined Data platform
Home-page: https://github.com/nevermined-io/contracts
Author: nevermined-io
Author-email: root@nevermined.io
License: Apache Software License 2.0
Keywords: nevermined-contracts
Classifier: Development Status :: 5 - Production/Stable
Classifier: Intended Audience :: Developers
Classifier: License :: OSI Approved :: Apache Software License
Classifier: Natural Language :: English
Classifier: Programming Language :: Python :: 3.7
Classifier: Programming Language :: Python :: 3.8
License-File: LICENSE
License-File: NOTICE
